Metadata-Version: 2.1
Name: plotly-helper
Version: 0.0.9
Summary: Package that makes plotly easy
Home-page: https://github.com/bluebrain/plotly-helper
Author: Blue Brain Project, EPFL
License: LGPLv3
Platform: UNKNOWN
Classifier: Development Status :: 2 - Pre-Alpha
Classifier: Programming Language :: Python
Classifier: Programming Language :: Python :: 3
Classifier: Programming Language :: Python :: 3.6
Requires-Python: >=3.6
Provides-Extra: docs
